{
  "config": {
    "abort": {
      "zha_not_configured": "Configure ZHA first, then add EasyIR."
    },
    "error": {
      "invalid_device": "Selected device was not found.",
      "unknown_ieee": "Could not read Zigbee IEEE from this device. Pick another ZHA device.",
      "invalid_profile": "Pick a built-in profile or enter a valid custom file path."
    },
    "step": {
      "user": {
        "title": "EasyIR",
        "description": "Pick your ZHA IR device (picker prefers TS1201 models). Built-in profiles ship with EasyIR; custom path is optional.%optional_supported",
        "data": {
          "zha_device": "ZHA device",
          "profile_choice": "IR profile",
          "profile_path": "Custom profile path (only if you chose Custom path)",
          "endpoint_id": "Default endpoint id"
        }
      }
    }
  },
  "services": {
    "start_learn": {
      "name": "Start IR learn mode",
      "description": "Enable hub learn mode and optionally auto-read one learned IR code.",
      "fields": {
        "ieee": {
          "name": "IEEE",
          "description": "Optional if default IEEE is set in integration entry."
        },
        "endpoint_id": {
          "name": "Endpoint id",
          "description": "Optional endpoint id (default 1)."
        },
        "model_hint": {
          "name": "Model hint",
          "description": "Optional adapter hint (e.g. ts1201_zosung)."
        },
        "auto_read": {
          "name": "Auto read",
          "description": "If true, poll/read one learned code and stop learn automatically."
        },
        "timeout_sec": {
          "name": "Timeout seconds",
          "description": "Max wait for one learned code in auto-read mode."
        },
        "poll_interval_sec": {
          "name": "Poll interval seconds",
          "description": "Polling interval while waiting for learned code."
        }
      }
    },
    "read_learned_code": {
      "name": "Read learned IR code",
      "description": "Read last learned code attribute and emit EasyIR learned-code event.",
      "fields": {
        "ieee": {
          "name": "IEEE",
          "description": "Optional if default IEEE is set in integration entry."
        },
        "endpoint_id": {
          "name": "Endpoint id",
          "description": "Optional endpoint id (default 1)."
        },
        "model_hint": {
          "name": "Model hint",
          "description": "Optional adapter hint (e.g. ts1201_zosung)."
        }
      }
    },
    "stop_learn": {
      "name": "Stop IR learn mode",
      "description": "Disable hub learn mode.",
      "fields": {
        "ieee": {
          "name": "IEEE",
          "description": "Optional if default IEEE is set in integration entry."
        },
        "endpoint_id": {
          "name": "Endpoint id",
          "description": "Optional endpoint id (default 1)."
        },
        "model_hint": {
          "name": "Model hint",
          "description": "Optional adapter hint (e.g. ts1201_zosung)."
        }
      }
    }
  }
}
